pt_lambdata/__init__.py
pt_lambdata/ds_utilities.py
pt_lambdata/test_functions.py
pt_lambdata-0.0.2.dist-info/LICENSE
pt_lambdata-0.0.2.dist-info/METADATA
pt_lambdata-0.0.2.dist-info/WHEEL
pt_lambdata-0.0.2.dist-info/top_level.txt
pt_lambdata-0.0.2.dist-info/RECORD
