Metadata-Version: 2.1
Name: pt-lambdata
Version: 0.0.2
Summary: A small collection of basic data utility functions.
Home-page: https://github.com/paulteeter/lambdata-paulteeter
Author: Paul Teeter
Author-email: paul-teeter@lambdastudents.com
License: MIT
Platform: UNKNOWN
